btlmp/__init__.py
btlmp/pytransform/__init__.py
btlmp/pytransform/platforms/linux/aarch64/_pytransform.so
btlmp/pytransform/platforms/linux/x86_64/_pytransform.so
btlmp-0.0.3.dist-info/LICENSE.txt
btlmp-0.0.3.dist-info/METADATA
btlmp-0.0.3.dist-info/WHEEL
btlmp-0.0.3.dist-info/entry_points.txt
btlmp-0.0.3.dist-info/top_level.txt
btlmp-0.0.3.dist-info/RECORD
