Metadata-Version: 2.1
Name: btlmp
Version: 0.0.3
Summary: Bluetooth LMP Utilities
Home-page: UNKNOWN
Author: Cibo
Author-email: cibo@bio-electric.com
License: UNKNOWN
Platform: UNKNOWN
Classifier: Operating System :: POSIX :: Linux
Classifier: Environment :: Console
Classifier: Programming Language :: Python :: 3
Classifier: Programming Language :: Python :: 3 :: Only
Classifier: Programming Language :: Python :: 3.10
Classifier: License :: Other/Proprietary License
Requires-Python: ==3.10.*
License-File: LICENSE.txt
Requires-Dist: pyclui (>=0.0.18)
Requires-Dist: xpycommon (>=0.0.13)
